mlbase/__init__.py
mlbase/jarvis.py
mlbase-0.1.0.dist-info/LICENSE
mlbase-0.1.0.dist-info/WHEEL
mlbase-0.1.0.dist-info/METADATA
mlbase-0.1.0.dist-info/RECORD
